__init__.py
app.py
configuration.py
main.py
endpoints/__init__.py
endpoints/compile_req.py
endpoints/generate_img.py
endpoints/pip_compile.py
models/__init__.py
models/database.py
models/environment.py
schemas/__init__.py
schemas/environment.py
utils/__init__.py
utils/exception.py
utils/logger.py
compilepy-0.1.dist-info/LICENSE.txt
compilepy-0.1.dist-info/METADATA
compilepy-0.1.dist-info/WHEEL
compilepy-0.1.dist-info/top_level.txt
compilepy-0.1.dist-info/RECORD
