Metadata-Version: 2.1
Name: compilepy
Version: 0.1
Summary: API for Dataflow ENV
Author: Digital Back Office
License: MIT
Keywords: compile
Classifier: Development Status :: 1 - Planning
Classifier: Intended Audience :: Developers
Classifier: Programming Language :: Python :: 3
Classifier: Operating System :: Unix
Classifier: Operating System :: MacOS :: MacOS X
Classifier: Operating System :: Microsoft :: Windows
License-File: LICENSE.txt
Requires-Dist: annotated-types (==0.6.0)
Requires-Dist: anyio (==4.3.0)
Requires-Dist: build (==1.2.1)
Requires-Dist: certifi (==2024.2.2)
Requires-Dist: charset-normalizer (==3.3.2)
Requires-Dist: click (==8.1.7)
Requires-Dist: colorama (==0.4.6)
Requires-Dist: fastapi (==0.110.1)
Requires-Dist: greenlet (==3.0.3)
Requires-Dist: h11 (==0.14.0)
Requires-Dist: httpcore (==1.0.5)
Requires-Dist: httpx (==0.27.0)
Requires-Dist: idna (==3.6)
Requires-Dist: iniconfig (==2.0.0)
Requires-Dist: packaging (==24.0)
Requires-Dist: pip-tools (==7.4.1)
Requires-Dist: pluggy (==1.4.0)
Requires-Dist: pydantic (==2.6.4)
Requires-Dist: pydantic-core (==2.16.3)
Requires-Dist: pyproject-hooks (==1.0.0)
Requires-Dist: pytest (==8.1.1)
Requires-Dist: requests (==2.31.0)
Requires-Dist: sniffio (==1.3.1)
Requires-Dist: SQLAlchemy (==2.0.29)
Requires-Dist: starlette (==0.37.2)
Requires-Dist: typing-extensions (==4.11.0)
Requires-Dist: urllib3 (==2.2.1)
Requires-Dist: uvicorn (==0.29.0)
